treediskpith/__init__.py
treediskpith/cli.py
treediskpith/config.py
treediskpith/detection/__init__.py
treediskpith/detection/pith_detection.py
treediskpith/detector.py
treediskpith/main.py
treediskpith/processing/__init__.py
treediskpith/processing/image_processing.py
treediskpith/utils/__init__.py
treediskpith/utils/file_utils.py
treediskpith/visualization/__init__.py
treediskpith/visualization/color.py
tree_disk_pith-0.2.1.dist-info/METADATA
tree_disk_pith-0.2.1.dist-info/WHEEL
tree_disk_pith-0.2.1.dist-info/entry_points.txt
tree_disk_pith-0.2.1.dist-info/RECORD
