Metadata-Version: 2.3
Name: tree-disk-pith
Version: 0.2.1
Summary: A package for tree disk pith detection in images
License: MIT
Keywords: tree,pith,image processing
Author: Tony
Author-email: tonymeissner70@gmail.com
Requires-Python: >=3.10
Classifier: License :: OSI Approved :: MIT License
Classifier: Programming Language :: Python :: 3
Classifier: Programming Language :: Python :: 3.10
Classifier: Programming Language :: Python :: 3.11
Classifier: Programming Language :: Python :: 3.12
Classifier: Programming Language :: Python :: 3.13
Requires-Dist: matplotlib (>=3.9.2,<4.0.0)
Requires-Dist: numpy (>=1.23.0,<2.0.0)
Requires-Dist: opencv-python (>=4.10.0.84,<5.0.0.0)
Requires-Dist: pandas (>=2.2.3,<3.0.0)
Requires-Dist: pillow (>=11.0.0,<12.0.0)
Requires-Dist: scikit-image (>=0.24.0,<0.25.0)
Requires-Dist: scikit-learn (>=1.5.2,<2.0.0)
Requires-Dist: ultralytics (>=8.3.28,<9.0.0)
Project-URL: Homepage, https://github.com/tuke307/tree-disk-analyzer
Project-URL: Repository, https://github.com/tuke307/tree-disk-analyzer
